ukritlib/__init__.py
ukritlib/function1.py
ukritlib/function2.py
ukritlib/tests/__init__.py
ukritlib/tests/test_joke.py
ukritlib-0.3.13.dist-info/METADATA
ukritlib-0.3.13.dist-info/WHEEL
ukritlib-0.3.13.dist-info/top_level.txt
ukritlib-0.3.13.dist-info/RECORD
